{
  "name": "Quarterstaff",
  "classes": [
    "Barbarian",
    "Wizard",
    "Cleric",
    "Warlock",
    "Druid",
    "Sorcerer"
  ],
  "damageRatings": {
    "1": [
      34
    ],
    "2": [
      35
    ],
    "3": [
      36
    ],
    "4": [
      37
    ],
    "5": [
      38
    ],
    "6": [
      39
    ],
    "7": [
      40
    ]
  },
  "moveSpeed": {
    "1": -30
  },
  "moveSpeedBonus": 0,
  "damageTypes": [
    "Slash",
    "Slash",
    "Slash"
  ],
  "impactZones": [
    100,
    100,
    100
  ],
  "impactPower": 0,
  "comboDamage": [
    100,
    100,
    100
  ],
  "type": [
    "mace",
    "staff",
    "Mace",
    "Staff"
  ],
  "rarities": [
    1,
    2,
    3,
    4,
    5,
    6,
    7
  ],
  "handType": "Two Handed",
  "slotType": "Main Hand",
  "gearScore": {},
  "invWidth": 1,
  "invHeight": 5,
  "flavorText": "Crafted from hardwood, this long shaft is a traditional and reliable weapon and tool.",
  "ap": {},
  "xp": {},
  "numEnchants": {},
  "maxHealthAdd": {},
  "maxHealthBonus": {},
  "magicalResistance": {},
  "projectileReduction": 0,
  "projectileReductionRate": {},
  "headshotReduction": 0,
  "BaseAttribute": {
    "strength": {},
    "vigor": {},
    "agility": {},
    "dexterity": {},
    "will": {},
    "knowledge": {},
    "resourcefulness": {}
  },
  "physicalPower": 0,
  "armorPenetration": 0,
  "magicPenetration": 0,
  "buffDuration": 0,
  "magicalPower": {},
  "magicalPowerBonus": {},
  "regularInteraction": {},
  "magicalHealing": {},
  "actionSpeed": {},
  "magicalDamageReduction": 0,
  "physicalDamageReduction": 0,
  "luck": 0,
  "armorRating": {},
  "impactResistance": 4,
  "artifactName": "Stinky Stick",
  "maxAmmoCount": 0,
  "maxCount": 1,
  "wearingDelayTime": 0,
  "unequipTime": 1,
  "sellPrices": {}
}